{
  "mode": "pre",
  "tag": "alpha",
  "initialVersions": {
    "@italia/button": "0.0.0",
    "@italia/dev-kit-italia": "0.0.0",
    "@italia/globals": "0.0.0",
    "@italia/icon": "0.0.0",
    "@italia/tabs": "0.0.0",
    "@italia/test-config": "0.0.0",
    "@italia/typescript-config": "0.0.0",
    "@italia/video": "0.0.0",
    "@italia/i18n": "0.0.0",
    "@italia/input": "0.0.0",
    "@italia/accordion": "0.0.0",
    "@italia/avatar": "0.1.0-alpha.1",
    "@italia/chip": "0.0.0",
    "@italia/dropdown": "0.0.0",
    "@italia/popover": "0.0.0",
    "@italia/radio": "0.0.0",
    "@italia/section": "0.0.0",
    "@italia/sticky": "0.0.0",
    "@italia/checkbox": "0.1.0-alpha.0",
    "@italia/collapse": "0.0.0",
    "@italia/skiplinks": "0.1.0-alpha.1"
  },
  "changesets": [
    "better-dancers-switch",
    "big-queens-cover",
    "blue-deer-walk",
    "bumpy-colts-buy",
    "bumpy-parrots-fall",
    "clean-jokes-unite",
    "clean-shrimps-remain",
    "common-rice-type",
    "cool-aliens-cheer",
    "cyan-lemons-flow",
    "early-parts-wear",
    "eight-tips-rest",
    "evil-chicken-help",
    "fast-tables-knock",
    "free-aliens-stay",
    "free-buses-begin",
    "huge-suns-switch",
    "icy-loops-wash",
    "large-planes-sleep",
    "legal-pillows-flow",
    "legal-tips-invite",
    "many-sheep-joke",
    "modern-plums-yell",
    "public-seas-smash",
    "purple-glasses-appear",
    "red-banks-attack",
    "rotten-turtles-clean",
    "rude-lemons-travel",
    "salty-lions-lay",
    "salty-yaks-rush",
    "short-ads-sniff",
    "social-paths-post",
    "soft-humans-bake",
    "stale-lizards-run",
    "thick-views-make",
    "thirty-trees-roll",
    "three-suits-peel",
    "violet-eagles-scream",
    "weak-nails-dance",
    "wet-lines-exist",
    "wise-rooms-kick",
    "witty-deer-love"
  ]
}
